plt/__init__.py
plt/plt
plt/templates/python/matplotlib/density.py
plt/templates/python/matplotlib/histogram.py
plt/templates/python/matplotlib/line.py
plt/templates/python/matplotlib/line_2d.py
plt/templates/python/matplotlib/normalized_histogram.py
plt/templates/python/matplotlib/scatter.py
plt/templates/python/plotext/density.py
plt/templates/python/plotext/histogram.py
plt/templates/python/plotext/line.py
plt/templates/python/plotext/line_2d.py
plt/templates/python/plotext/scatter.py
plt_cli-0.2.7.data/scripts/plt
plt_cli-0.2.7.dist-info/licenses/LICENSE
plt_cli-0.2.7.dist-info/METADATA
plt_cli-0.2.7.dist-info/WHEEL
plt_cli-0.2.7.dist-info/top_level.txt
plt_cli-0.2.7.dist-info/RECORD
