Metadata-Version: 2.4
Name: plt-cli
Version: 0.2.7
Summary: A CLI plotting utility
Home-page: https://github.com/rlschuller/plt
Author: Rodrigo Loro Schuller
Author-email: rloroschuller@gmail.com
Project-URL: Bug Tracker, https://github.com/rlschuller/plt/issues
Classifier: Programming Language :: Python :: 3
Classifier: License :: OSI Approved :: MIT License
Classifier: Operating System :: OS Independent
Requires-Python: >=3.6
License-File: LICENSE
Requires-Dist: matplotlib
Requires-Dist: plotext
Requires-Dist: importlib_resources
Dynamic: license-file
